pooraka/__init__.py
pooraka/autoaugment.py
pooraka/dataset.py
pooraka/flops_counter.py
pooraka/fmix.py
pooraka/inference.py
pooraka/meanstd.py
pooraka/mix.py
pooraka/trainer.py
pooraka/utils.py
pooraka/version.py
pooraka-0.2.6.dist-info/LICENSE
pooraka-0.2.6.dist-info/METADATA
pooraka-0.2.6.dist-info/WHEEL
pooraka-0.2.6.dist-info/top_level.txt
pooraka-0.2.6.dist-info/RECORD
